aclib/autowin/__init__.py
aclib/autowin/cvwindow.py
aclib/autowin/dmwindow.py
aclib/autowin/__API__/_typing.py
aclib/autowin/__API__/basewindow.py
aclib/autowin/__API__/cvwindow.py
aclib/autowin/__API__/dmwindow.py
aclib/autowin/__API__/screen.py
aclib/autowin/__API__/window.py
aclib/autowin/appwindow/__init__.py
aclib/autowin/appwindow/_typing.py
aclib/autowin/appwindow/appwindow.py
aclib/autowin/appwindow/background.py
aclib/autowin/appwindow/pytypes.py
aclib_autowin-1.5.1.dist-info/licenses/LICENSE
aclib_autowin-1.5.1.dist-info/METADATA
aclib_autowin-1.5.1.dist-info/WHEEL
aclib_autowin-1.5.1.dist-info/top_level.txt
aclib_autowin-1.5.1.dist-info/RECORD
