Metadata-Version: 2.4
Name: aclib.autowin
Version: 1.5.1
Summary: auto window task
Home-page: https://github.com/AnsChaser/aclib.autowin
Author: AnsChaser
Author-email: anschaser@163.com
License: MIT
Classifier: Development Status :: 5 - Production/Stable
Classifier: Intended Audience :: Developers
Classifier: Topic :: Software Development :: Libraries :: Python Modules
Classifier: License :: OSI Approved :: MIT License
Classifier: Programming Language :: Python :: 3
Classifier: Programming Language :: Python :: 3 :: Only
Classifier: Programming Language :: Python :: 3.6
Classifier: Programming Language :: Python :: 3.7
Classifier: Programming Language :: Python :: 3.8
Classifier: Programming Language :: Python :: 3.9
Classifier: Programming Language :: Python :: 3.10
Classifier: Programming Language :: Python :: 3.11
Classifier: Programming Language :: Python :: 3.12
Requires-Python: >=3.6
License-File: LICENSE
Requires-Dist: aclib.builtins
Requires-Dist: aclib.winlib
Provides-Extra: cv
Requires-Dist: aclib.cv; extra == "cv"
Provides-Extra: dm
Requires-Dist: aclib.dm; extra == "dm"
Provides-Extra: full
Requires-Dist: aclib.autowin[cv,dm]; extra == "full"
Provides-Extra: dev
Requires-Dist: aclib.autowin[full]; extra == "dev"
Requires-Dist: aclib.pip; extra == "dev"
Requires-Dist: build; extra == "dev"
Requires-Dist: twine; extra == "dev"
Dynamic: author
Dynamic: author-email
Dynamic: classifier
Dynamic: description
Dynamic: description-content-type
Dynamic: home-page
Dynamic: license
Dynamic: license-file
Dynamic: provides-extra
Dynamic: requires-dist
Dynamic: requires-python
Dynamic: summary
